tests/golden/counter.v
module Counter #(
    parameter WIDTH = 8
) (
    input wire clk,
    input wire rst,
    output wire [(WIDTH)-1:0] count
);
    reg [(WIDTH)-1:0] value;
    // NOTE (BUG-65, docs/audit/bugs.md): the `initial` register-init line(s) below are simulation/FPGA-only - an ASIC flow has no defined power-on default and will not honor them. The synchronous reset below still applies regardless.
    initial #0 value = 0;
    assign count = value;
    always @(posedge clk) begin
        if (rst) begin
            value <= 0;
        end else begin
            value <= (value + 8'd1);
        end
    end
endmodule

tests/golden/counter.vcd
$timescale 1ns $end
$scope module Counter $end
$var wire 1 ! clk $end
$var wire 1 " rst $end
$var wire 8 # value $end
$var wire 8 $ count $end
$upscope $end
$enddefinitions $end
#0
$dumpvars
1!
1"
b0 #
b0 $
$end
#5
0!
#10
1!
0"
b1 #
b1 $
#15
0!
#20
1!
b10 #
b10 $
#25
0!
#30
1!
b11 #
b11 $
#35
0!
#40
1!
b100 #
b100 $
#45
0!
#50
1!
b101 #
b101 $
#55
0!
#60
1!
b110 #
b110 $
#65
0!
#70
1!
b111 #
b111 $
